tripod/README.md
tripod/__init__.py
tripod/exceptions.py
tripod/local.py
tripod/main.py
tripod/tasks.py
tripod/utils.py
tripod/application/__init__.py
tripod/application/blueprint.py
tripod/application/daemon.py
tripod/application/flask.py
tripod/application/gunicorn.py
tripod/application/supervisor.py
tripod/application/app_factory/__init__.py
tripod/application/app_factory/daemon_factory.py
tripod/application/app_factory/flask_factory.py
tripod/builders/__init__.py
tripod/builders/daemon_builder.py
tripod/builders/flask_loaders.py
tripod/config/__init__.py
tripod/config/config.py
tripod/events/__init__.py
tripod/events/app_event.py
tripod/events/app_hooks.py
tripod/template_builders/__init__.py
tripod/template_builders/flask_builders.py
tripod/template_builders/supervisor_builder.py
tripod/tests/tripod-test/__init__.py
tripod/tests/tripod-test/main.py
tripod/tests/tripod-test/tripod_hooks.py
tripod/tests/tripod-test/settings/__init__.py
tripod/tests/tripod-test/settings/settings.py
tripod/tests/tripod-test/tasks/__init__.py
tripod/tests/tripod-test/tasks/mysql.py
tripod_lrn-0.0.14.dist-info/METADATA
tripod_lrn-0.0.14.dist-info/RECORD
tripod_lrn-0.0.14.dist-info/WHEEL
tripod_lrn-0.0.14.dist-info/entry_points.txt
tripod_lrn-0.0.14.dist-info/top_level.txt
