Metadata-Version: 2.1
Name: tripod-lrn
Version: 0.0.14
Summary: Utility project code.
Home-page: UNKNOWN
Author: Luis Felipe Muller
Author-email: luisfmuller@gmail.com
License: UNKNOWN
Platform: UNKNOWN
Requires-Dist: arrow (==0.12.1)
Requires-Dist: atomicwrites (==1.1.5)
Requires-Dist: attrs (==18.1.0)
Requires-Dist: binaryornot (==0.4.4)
Requires-Dist: blinker (==1.4)
Requires-Dist: certifi (==2018.8.13)
Requires-Dist: chardet (==3.0.4)
Requires-Dist: click (==6.7)
Requires-Dist: cookiecutter (==1.6.0)
Requires-Dist: coverage (==4.5.1)
Requires-Dist: future (==0.16.0)
Requires-Dist: idna (==2.7)
Requires-Dist: invoke (>=1.1.1)
Requires-Dist: jinja2-time (==0.2.0)
Requires-Dist: jinja2 (==2.10)
Requires-Dist: markupsafe (==1.0)
Requires-Dist: more-itertools (==4.3.0)
Requires-Dist: poyo (==0.4.1)
Requires-Dist: py (==1.5.4)
Requires-Dist: pytest-cov (==2.5.1)
Requires-Dist: pytest (==3.7.1)
Requires-Dist: python-dateutil (==2.7.3)
Requires-Dist: pyyaml (==3.13)
Requires-Dist: requests (==2.19.1)
Requires-Dist: six (==1.11.0)
Requires-Dist: urllib3 (==1.23)
Requires-Dist: whichcraft (==0.4.1)
Requires-Dist: pluggy (==0.7.1); python_version != "3.2.*"
Requires-Dist: pathlib2 (==2.3.2); python_version < "3.6"
